gf2_irreducibles/__init__.py
gf2_irreducibles/polys.py
gf2_irreducibles/utils.py
gf2_irreducibles-0.1.3.dist-info/LICENSE
gf2_irreducibles-0.1.3.dist-info/METADATA
gf2_irreducibles-0.1.3.dist-info/WHEEL
gf2_irreducibles-0.1.3.dist-info/top_level.txt
gf2_irreducibles-0.1.3.dist-info/RECORD
