Metadata-Version: 2.1
Name: gf2-irreducibles
Version: 0.1.3
Summary: Lookup table for low-weight binary irreducible polynomials (GF(2^n)).
Home-page: https://github.com/Gad1001/gf2-irreducibles
Author: Gad E. Yaron
Author-email: gadelaz.yaron@mail.huji.ac.il
Classifier: Programming Language :: Python :: 3
Classifier: License :: OSI Approved :: MIT License
Classifier: Operating System :: OS Independent
Classifier: Topic :: Security :: Cryptography
Classifier: Topic :: Scientific/Engineering :: Mathematics
Requires-Python: >=3.6
License-File: LICENSE
